logiclib/__init__.py
logiclib/__main__.py
logiclib/formula.py
logiclib/parser.py
logiclib-0.0.1.post5.dist-info/METADATA
logiclib-0.0.1.post5.dist-info/WHEEL
logiclib-0.0.1.post5.dist-info/licenses/LICENSE
logiclib-0.0.1.post5.dist-info/RECORD
